twitterbot/TwitterBot.py
twitterbot/__init__.py
twitterbot/scripts/__init__.py
twitterbot/scripts/delete_tweets.py
twitterbot/scripts/get_trending.py
twitterbot/scripts/remove_favorites.py
twitterbot/scripts/utils.py
salahs_twitterbot-1.3.1.dist-info/METADATA
salahs_twitterbot-1.3.1.dist-info/WHEEL
salahs_twitterbot-1.3.1.dist-info/entry_points.txt
salahs_twitterbot-1.3.1.dist-info/top_level.txt
salahs_twitterbot-1.3.1.dist-info/RECORD
