Metadata-Version: 2.1
Name: salahs-twitterbot
Version: 1.3.1
Summary: twitterbot to remove/view favorites/tweets and view trending tweets
Home-page: https://github.com/salah93/twitterbot
Author: Salah Ahmed
Author-email: salah93@crosscompute.com
License: UNKNOWN
Keywords: web twitterbot twitter
Platform: UNKNOWN
Classifier: Programming Language :: Python
Classifier: Topic :: Internet :: WWW/HTTP :: WSGI :: Application
Classifier: License :: OSI Approved :: MIT License
Requires-Dist: oauth2 (<2.0.0,>=1.9.0.post1)
Provides-Extra: scripts
Requires-Dist: yweather (<1.0,>=0.1) ; extra == 'scripts'
Provides-Extra: test
Requires-Dist: pytest-coverage ; extra == 'test'
Requires-Dist: httpretty (<1.0.0,>=0.9.6) ; extra == 'test'
Requires-Dist: coverage[toml] ; extra == 'test'
